croatian_holidays/__init__.py
croatian_holidays-0.1.4.dist-info/licenses/LICENSE
croatian_holidays-0.1.4.dist-info/METADATA
croatian_holidays-0.1.4.dist-info/WHEEL
croatian_holidays-0.1.4.dist-info/top_level.txt
croatian_holidays-0.1.4.dist-info/RECORD
