Metadata-Version: 2.4
Name: croatian-holidays
Version: 0.1.4
Summary: Python library for Croatian public holidays with computed Easter/Corpus Christi, fixed national holiday dates, and optional web scraping.
Author-email: Matija Gračanin <matijag@gmail.com>
License: MIT
Project-URL: Homepage, https://github.com/mgracanin/croatian-holidays
Project-URL: Repository, https://github.com/mgracanin/croatian-holidays
Project-URL: Issues, https://github.com/mgracanin/croatian-holidays/issues
Keywords: croatia,holidays,calendar,dates,easter,corpus-christi
Classifier: Development Status :: 3 - Alpha
Classifier: Intended Audience :: Developers
Classifier: License :: OSI Approved :: MIT License
Classifier: Programming Language :: Python
Classifier: Programming Language :: Python :: 3
Classifier: Programming Language :: Python :: 3 :: Only
Classifier: Programming Language :: Python :: 3.8
Classifier: Programming Language :: Python :: 3.9
Classifier: Programming Language :: Python :: 3.10
Classifier: Programming Language :: Python :: 3.11
Classifier: Programming Language :: Python :: 3.12
Classifier: Topic :: Software Development :: Libraries
Classifier: Typing :: Typed
Requires-Python: >=3.8
License-File: LICENSE
Requires-Dist: requests>=2.28
Requires-Dist: beautifulsoup4>=4.10
Dynamic: license-file
